mamba/__init__.py
mamba/__main__.py
mamba/tools.py
mamba/commands/__init__.py
mamba/commands/build.py
mamba/commands/new.py
mamba_toolbox-1.2.6.23.dist-info/METADATA
mamba_toolbox-1.2.6.23.dist-info/WHEEL
mamba_toolbox-1.2.6.23.dist-info/entry_points.txt
mamba_toolbox-1.2.6.23.dist-info/top_level.txt
mamba_toolbox-1.2.6.23.dist-info/RECORD
