Metadata-Version: 2.1
Name: mamba-toolbox
Version: 1.2.6.23
Summary: Mambalib toolbox
Requires-Dist: click ==8.1.7
Requires-Dist: requests ==2.31.0
Requires-Dist: virtualenv ==20.25.0
